{"web":{"client_id":"1066864495489-a36j2vv904kp4tkptnvo80gsp40stnca.apps.googleusercontent.com","project_id":"zippy-folio-438703-h3","auth_uri":"https://accounts.google.com/o/oauth2/auth","token_uri":"https://oauth2.googleapis.com/token","auth_provider_x509_cert_url":"https://www.googleapis.com/oauth2/v1/certs","client_secret":"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","redirect_uris":["http://localhost","http://localhost:3000","https://edumocks.com"],"javascript_origins":["http://localhost","http://localhost:3000","https://edumocks.com"]}}

//1066864495489-a36j2vv904kp4tkptnvo80gsp40stnca.apps.googleusercontent.com